LICENSE
MANIFEST.in
README.md
requirements.txt
setup.py
django_postcodepy_proxy.egg-info/PKG-INFO
django_postcodepy_proxy.egg-info/SOURCES.txt
django_postcodepy_proxy.egg-info/dependency_links.txt
django_postcodepy_proxy.egg-info/requires.txt
django_postcodepy_proxy.egg-info/top_level.txt
postcodepy_proxy/__init__.py
postcodepy_proxy/signalapi.py
postcodepy_proxy/tests.py
postcodepy_proxy/views.py
tests/__init__.py
tests/settings.py
tests/test_PCpy.py