Metadata-Version: 1.1
Name: django-postcodepy-proxy
Version: 1.0.0
Summary: simple Django app to make your backend serve as a proxy for the postcode.nl REST-API
Home-page: https://github.com/hootnot/django-postcodepy-proxy
Author: Feite Brekeveld
Author-email: f.brekeveld@gmail.com
License: MIT
Keywords: postcode.nl REST API django proxy python
Platform: UNKNOWN
Classifier: Development Status :: 5 - Production/Stable
Classifier: Intended Audience :: Developers
Classifier: Topic :: Utilities
